clicksign_api_wrapper/__init__.py
clicksign_api_wrapper/batch.py
clicksign_api_wrapper/clicksign.py
clicksign_api_wrapper/document.py
clicksign_api_wrapper/exceptions.py
clicksign_api_wrapper/list.py
clicksign_api_wrapper/list_class.py
clicksign_api_wrapper/signer.py
clicksign_api_wrapper-0.0.4.dist-info/LICENSE
clicksign_api_wrapper-0.0.4.dist-info/METADATA
clicksign_api_wrapper-0.0.4.dist-info/WHEEL
clicksign_api_wrapper-0.0.4.dist-info/top_level.txt
clicksign_api_wrapper-0.0.4.dist-info/RECORD
