Metadata-Version: 2.1
Name: clicksign-api-wrapper
Version: 0.0.4
Summary: A simple Click Sign API Wrapper.
Home-page: https://github.com/balko/clicksign_api_wrapper
Author: LsMar
Author-email: lucas.smar@gmail.com
License: MIT License
Platform: UNKNOWN
Requires-Dist: requests
